device_tracker/__init__.py
device_tracker/admin.py
device_tracker/apps.py
device_tracker/middleware.py
device_tracker/models.py
device_tracker/tests.py
device_tracker/urls.py
device_tracker/utils.py
device_tracker/views.py
device_tracker/migrations/0001_initial.py
device_tracker/migrations/__init__.py
django_device_tracker/__init__.py
django_device_tracker/asgi.py
django_device_tracker/settings.py
django_device_tracker/urls.py
django_device_tracker/wsgi.py
django_device_tracker-0.3.0.dist-info/licenses/LICENSE
django_device_tracker-0.3.0.dist-info/METADATA
django_device_tracker-0.3.0.dist-info/WHEEL
django_device_tracker-0.3.0.dist-info/top_level.txt
django_device_tracker-0.3.0.dist-info/RECORD
